[{"type": "entry", "author": {"type": "card", "name": "", "photo": "", "url": ""}, "url": "http://appuntistudenteschi.altervista.org/escono-dalle-fottute-pareti/", "published": null, "wm-received": "2021-10-21T21:34:13Z", "wm-id": 1294830, "wm-source": "http://appuntistudenteschi.altervista.org/escono-dalle-fottute-pareti/", "wm-target": "https://fundor333.com", "wm-protocol": "webmention", "mention-of": "https://fundor333.com", "wm-property": "mention-of", "wm-private": false, "rels": {"canonical": "http://appuntistudenteschi.altervista.org/escono-dalle-fottute-pareti/"}}]