[{"type": "entry", "author": {"type": "card", "name": "fundor333", "photo": "https://avatars.webmention.io/shiitake.us-east.host.bsky.network/745ae7c92d33ea40ee0a0cc07825d49dcf5f0375c9b77cf4404889a238e66f93.jpg", "url": "https://bsky.app/profile/fundor333.bsky.social"}, "url": "https://bsky.app/profile/did:plc:u7piwonv4s27ysugjaa6im2q/post/3lybtuiopzp2q", "published": "2025-09-07T23:27:46+00:00", "wm-received": "2025-09-07T23:30:44Z", "wm-id": 1937665, "wm-source": "https://bsky.brid.gy/convert/web/at://did:plc:u7piwonv4s27ysugjaa6im2q/app.bsky.feed.post/3lybtuiopzp2q%23bridgy-fed-create", "wm-target": "https://fundor333.com/micro/2025/09/more-test/", "wm-protocol": "webmention", "content": {"html": "More tests\n\n<a href=\"https://fundor333.com/micro/2025/09/more-test/\">https://fundor333.com/micro/2025/09/more-test/</a>\n\n<a href=\"https://bsky.app/search?q=%23test\">#test</a> <a href=\"https://bsky.app/search?q=%23dev\">#dev</a> <a href=\"https://bsky.app/search?q=%23bridgy\">#bridgy</a> (<a href=\"https://fundor333.com/micro/2025/09/more-test/\">https://fundor333.com/micro/2025/09/more-test/</a>)", "text": "More tests\n\nhttps://fundor333.com/micro/2025/09/more-test/\n\n#test #dev #bridgy (https://fundor333.com/micro/2025/09/more-test/)"}, "mention-of": "https://fundor333.com/micro/2025/09/more-test/", "wm-property": "mention-of", "wm-private": false}]